{
	"default": {
		"api_key": "MY-RIOT-API-KEY",
		"host": "{region}.api.riotgames.com",
		"season": 9
	},
	"development": {

	},
	"production": {

	},
	"region": {
		"RU": "ru",
		"KR": "kr",
		"BR1": "br1",
		"OC1": "oc1",
		"JP1": "jp1",
		"NA1": "na1",
		"EUN1": "eun1",
		"EUW1": "euw1",
		"TR1": "tr1",
		"LA1": "la1",
		"LA2": "la2"
	},
	"api": {
		"patch":"7.24.2",
		"summoner_v3": {
			"by_name":"/lol/summoner/v3/summoners/by-name/{summonerName}"
		},
		"match_v3": {
			"get_match": "/lol/match/v3/matches/{matchId}",
			"by_account": "/lol/match/v3/matchlists/by-account/{accountId}",
			"by_account_recent": "/lol/match/v3/matchlists/by-account/{accountId}/recent"
		}
	}
}